{"UGIS 188": {"units": [3, 3], "instructor": null, "id": null, "title": "Research Methods for Science and Mathematics K-12 Teachers", "sections": [{"time": {"startTime": null, "endTime": null, "days": null}, "printInScheduleOfClasses": true, "waitlisted": 0, "enrolled": 0, "location": null, "enrollCapacity": 24, "instructor": null, "id": null, "primary": true, "number": "1", "type": "SEM", "waitlistCapacity": 24}], "displayName": "UGIS 188"}, "UGIS 162K": {"units": [4, 4], "instructor": null, "id": null, "title": "Spies! The Politics of Intelligence", "sections": [{"time": {"startTime": null, "endTime": null, "days": null}, "printInScheduleOfClasses": true, "waitlisted": 0, "enrolled": 0, "location": null, "enrollCapacity": 16, "instructor": null, "id": null, "primary": true, "number": "1", "type": "LEC", "waitlistCapacity": 16}], "displayName": "UGIS 162K"}, "UGIS C196A": {"units": [4, 4], "instructor": null, "id": null, "title": "UCDC Core Seminar", "sections": [{"time": {"startTime": null, "endTime": null, "days": null}, "printInScheduleOfClasses": true, "waitlisted": 0, "enrolled": 0, "location": null, "enrollCapacity": 10, "instructor": null, "id": null, "primary": true, "number": "1", "type": "LEC", "waitlistCapacity": 10}], "displayName": "UGIS C196A"}, "UGIS 162M": {"units": [4, 4], "instructor": null, "id": null, "title": "U.S. Foreign Policy in the Middle East", "sections": [{"time": {"startTime": null, "endTime": null, "days": null}, "printInScheduleOfClasses": true, "waitlisted": 0, "enrolled": 0, "location": null, "enrollCapacity": 10, "instructor": null, "id": null, "primary": true, "number": "1", "type": "LEC", "waitlistCapacity": 1}], "displayName": "UGIS 162M"}, "UGIS 140": {"units": [2, 2], "instructor": null, "id": null, "title": "The Hand-Printed Book in Its Historical Context", "sections": [{"time": {"startTime": null, "endTime": null, "days": null}, "printInScheduleOfClasses": true, "waitlisted": 0, "enrolled": 0, "location": null, "enrollCapacity": 6, "instructor": null, "id": null, "primary": true, "number": "1", "type": "STD", "waitlistCapacity": 10}], "displayName": "UGIS 140"}, "UGIS 187": {"units": [4, 4], "instructor": null, "id": null, "title": "Project-Based Instruction", "sections": [{"time": {"startTime": null, "endTime": null, "days": null}, "printInScheduleOfClasses": true, "waitlisted": 0, "enrolled": 0, "location": null, "enrollCapacity": 32, "instructor": null, "id": null, "primary": true, "number": "1", "type": "LEC", "waitlistCapacity": 32}], "displayName": "UGIS 187"}, "UGIS 192B": {"units": [1, 4], "instructor": null, "id": null, "title": "Supervised Research: Social Sciences", "sections": [{"time": {"startTime": null, "endTime": null, "days": null}, "printInScheduleOfClasses": true, "waitlisted": 0, "enrolled": 0, "location": null, "enrollCapacity": 15, "instructor": null, "id": null, "primary": true, "number": "40", "type": "TUT", "waitlistCapacity": 15}], "displayName": "UGIS 192B"}, "UGIS 162O": {"units": [4, 4], "instructor": null, "id": null, "title": "The Science of Politics: Campaigns and Elections", "sections": [{"time": {"startTime": null, "endTime": null, "days": null}, "printInScheduleOfClasses": true, "waitlisted": 0, "enrolled": 0, "location": null, "enrollCapacity": 10, "instructor": null, "id": null, "primary": true, "number": "1", "type": "LEC", "waitlistCapacity": 10}], "displayName": "UGIS 162O"}, "UGIS 98": {"units": [1, 4], "instructor": null, "id": null, "title": "Directed Group Study for Lower Division Students", "sections": [{"time": {"startTime": null, "endTime": null, "days": null}, "printInScheduleOfClasses": true, "waitlisted": 0, "enrolled": 0, "location": null, "enrollCapacity": 20, "instructor": null, "id": null, "primary": true, "number": "1", "type": "GRP", "waitlistCapacity": 20}], "displayName": "UGIS 98"}, "UGIS C155": {"units": [4, 4], "instructor": null, "id": null, "title": "Jewish Civilization: Modern Period", "sections": [{"time": {"startTime": null, "endTime": null, "days": null}, "printInScheduleOfClasses": true, "waitlisted": 0, "enrolled": 0, "location": null, "enrollCapacity": 0, "instructor": null, "id": null, "primary": true, "number": "1", "type": "LEC", "waitlistCapacity": 0}], "displayName": "UGIS C155"}, "UGIS 192C": {"units": [1, 4], "instructor": null, "id": null, "title": "Supervised Research: Biological Sciences", "sections": [{"time": {"startTime": null, "endTime": null, "days": null}, "printInScheduleOfClasses": true, "waitlisted": 0, "enrolled": 0, "location": null, "enrollCapacity": 30, "instructor": null, "id": null, "primary": true, "number": "4", "type": "TUT", "waitlistCapacity": 30}], "displayName": "UGIS 192C"}, "UGIS 82": {"units": [2, 2], "instructor": null, "id": null, "title": "K-8 Teaching and Inquiry-Based Lesson Design in the Science and Mathematics Classroom", "sections": [{"time": {"startTime": null, "endTime": null, "days": null}, "printInScheduleOfClasses": true, "waitlisted": 0, "enrolled": 0, "location": null, "enrollCapacity": 30, "instructor": null, "id": null, "primary": true, "number": "1", "type": "SEM", "waitlistCapacity": 24}], "displayName": "UGIS 82"}, "UGIS 198": {"units": [1, 4], "instructor": null, "id": null, "title": "Directed Group Study for Upper Division Students", "sections": [{"time": {"startTime": null, "endTime": null, "days": null}, "printInScheduleOfClasses": true, "waitlisted": 0, "enrolled": 0, "location": null, "enrollCapacity": 20, "instructor": null, "id": null, "primary": true, "number": "3", "type": "GRP", "waitlistCapacity": 20}], "displayName": "UGIS 198"}, "UGIS 192A": {"units": [1, 4], "instructor": null, "id": null, "title": "Supervised Research: Humanities", "sections": [{"time": {"startTime": null, "endTime": null, "days": null}, "printInScheduleOfClasses": true, "waitlisted": 0, "enrolled": 0, "location": null, "enrollCapacity": 10, "instructor": null, "id": null, "primary": true, "number": "3", "type": "TUT", "waitlistCapacity": 10}], "displayName": "UGIS 192A"}, "UGIS 304": {"units": [5, 5], "instructor": null, "id": null, "title": "Supervised Teaching in Mathematics and Science for Secondary Schools", "sections": [{"time": {"startTime": null, "endTime": null, "days": null}, "printInScheduleOfClasses": true, "waitlisted": 0, "enrolled": 0, "location": null, "enrollCapacity": 15, "instructor": null, "id": null, "primary": true, "number": "1", "type": "FLD", "waitlistCapacity": 1}], "displayName": "UGIS 304"}, "UGIS C196B": {"units": [6.5, 6.5], "instructor": null, "id": null, "title": "UCDC Internship", "sections": [{"time": {"startTime": null, "endTime": null, "days": null}, "printInScheduleOfClasses": true, "waitlisted": 0, "enrolled": 0, "location": null, "enrollCapacity": 10, "instructor": null, "id": null, "primary": true, "number": "1", "type": "INT", "waitlistCapacity": 10}], "displayName": "UGIS C196B"}, "UGIS 160A": {"units": [4, 4], "instructor": null, "id": null, "title": "Art", "sections": [{"time": {"startTime": null, "endTime": null, "days": null}, "printInScheduleOfClasses": true, "waitlisted": 0, "enrolled": 0, "location": null, "enrollCapacity": 10, "instructor": null, "id": null, "primary": true, "number": "1", "type": "LEC", "waitlistCapacity": 10}], "displayName": "UGIS 160A"}, "UGIS 303": {"units": [2, 3], "instructor": null, "id": null, "title": "Apprentice Teaching in Science and Mathematics", "sections": [{"time": {"startTime": null, "endTime": null, "days": null}, "printInScheduleOfClasses": true, "waitlisted": 0, "enrolled": 0, "location": null, "enrollCapacity": 32, "instructor": null, "id": null, "primary": true, "number": "1", "type": "SEM", "waitlistCapacity": 32}], "displayName": "UGIS 303"}, "UGIS 175": {"units": [4, 4], "instructor": null, "id": null, "title": "Washington Ethics: Crisis, Reform, and Reaction", "sections": [{"time": {"startTime": null, "endTime": null, "days": null}, "printInScheduleOfClasses": true, "waitlisted": 0, "enrolled": 0, "location": null, "enrollCapacity": 10, "instructor": null, "id": null, "primary": true, "number": "1", "type": "LEC", "waitlistCapacity": 10}], "displayName": "UGIS 175"}, "UGIS 192E": {"units": [1, 4], "instructor": null, "id": null, "title": "Supervised Research: Interdisciplinary Studies", "sections": [{"time": {"startTime": null, "endTime": null, "days": null}, "printInScheduleOfClasses": true, "waitlisted": 0, "enrolled": 0, "location": null, "enrollCapacity": 20, "instructor": null, "id": null, "primary": true, "number": "36", "type": "TUT", "waitlistCapacity": 20}], "displayName": "UGIS 192E"}, "UGIS 192D": {"units": [1, 4], "instructor": null, "id": null, "title": "Supervised Research: Physical Sciences", "sections": [{"time": {"startTime": null, "endTime": null, "days": null}, "printInScheduleOfClasses": true, "waitlisted": 0, "enrolled": 0, "location": null, "enrollCapacity": 15, "instructor": null, "id": null, "primary": true, "number": "18", "type": "TUT", "waitlistCapacity": 15}], "displayName": "UGIS 192D"}, "UGIS 120": {"units": [3, 3], "instructor": null, "id": null, "title": "Introduction to Applied Language Studies", "sections": [{"time": {"startTime": null, "endTime": null, "days": null}, "printInScheduleOfClasses": true, "waitlisted": 0, "enrolled": 1, "location": null, "enrollCapacity": 50, "instructor": null, "id": null, "primary": true, "number": "1", "type": "LEC", "waitlistCapacity": 10}], "displayName": "UGIS 120"}, "UGIS 162N": {"units": [4, 4], "instructor": null, "id": null, "title": "American Political Journalism", "sections": [{"time": {"startTime": null, "endTime": null, "days": null}, "printInScheduleOfClasses": true, "waitlisted": 0, "enrolled": 0, "location": null, "enrollCapacity": 10, "instructor": null, "id": null, "primary": true, "number": "1", "type": "LEC", "waitlistCapacity": 10}], "displayName": "UGIS 162N"}, "UGIS 110": {"units": [3, 3], "instructor": null, "id": null, "title": "Introduction to Disability Studies", "sections": [{"time": {"startTime": null, "endTime": null, "days": null}, "printInScheduleOfClasses": true, "waitlisted": 0, "enrolled": 16, "location": null, "enrollCapacity": 50, "instructor": null, "id": null, "primary": true, "number": "1", "type": "LEC", "waitlistCapacity": 5}], "displayName": "UGIS 110"}, "UGIS 162I": {"units": [4, 4], "instructor": null, "id": null, "title": "Political Science: Lobbying, Money, and Influence in Washington", "sections": [{"time": {"startTime": null, "endTime": null, "days": null}, "printInScheduleOfClasses": true, "waitlisted": 0, "enrolled": 0, "location": null, "enrollCapacity": 10, "instructor": null, "id": null, "primary": true, "number": "1", "type": "LEC", "waitlistCapacity": 10}], "displayName": "UGIS 162I"}, "UGIS 162L": {"units": [4, 4], "instructor": null, "id": null, "title": "Middle East Politics and the Arab \"Spring\"", "sections": [{"time": {"startTime": null, "endTime": null, "days": null}, "printInScheduleOfClasses": true, "waitlisted": 0, "enrolled": 0, "location": null, "enrollCapacity": 10, "instructor": null, "id": null, "primary": true, "number": "1", "type": "LEC", "waitlistCapacity": 10}], "displayName": "UGIS 162L"}}