{"27A": [{"sAC": "BOSCRSR", "enrollment": {"wCurr": 0, "eMax": 15, "eMin": 0, "eCurr": 0, "wMax": 3}, "units": {"maximum": 4, "minimum": 4}, "description": "Beginner's course. Sequence beginning Fall semester. ", "priComp": "LEC", "id": 13115, "number": "001", "title": "Introductory Bosnian/Croatian/Serbian", "fExam": {"description": "Yes", "code": "Y"}, "cN": "27A", "status": "A", "grading": "OPT", "sections": [{"type": "LEC", "enrollment": {"wCurr": 0, "eMax": 15, "eMin": 0, "eCurr": 0, "wMax": 3}, "graded": true, "meetings": [{"instructors": [], "loc": {"description": "Dwinelle 210", "code": "DWIN210"}, "days": {"Mo": true, "Su": false, "We": true, "Th": false, "Sa": false, "Tu": false, "Fr": true}, "eT": "12:59:00", "sT": "12:00:00", "dayAbbrevs": "MoWeFr"}], "isPri": true, "status": {"description": "Open", "code": "O"}, "assocPriSecId": 13115, "id": 13115, "number": "001"}], "crossListed": null, "instructionMode": "P"}], "117A": [{"sAC": "BOSCRSR", "enrollment": {"wCurr": 0, "eMax": 15, "eMin": 0, "eCurr": 0, "wMax": 3}, "units": {"maximum": 4, "minimum": 4}, "description": "Sequence begins fall semester. ", "priComp": "LEC", "id": 13106, "number": "001", "title": "Continuing Bosnian/Croatian/Serbian", "fExam": {"description": "Yes", "code": "Y"}, "cN": "117A", "status": "A", "grading": "OPT", "sections": [{"type": "LEC", "enrollment": {"wCurr": 0, "eMax": 15, "eMin": 0, "eCurr": 0, "wMax": 3}, "graded": true, "meetings": [{"instructors": [], "loc": {"description": "Dwinelle 6307", "code": "DWIN6307"}, "days": {"Mo": true, "Su": false, "We": true, "Th": false, "Sa": false, "Tu": false, "Fr": true}, "eT": "12:59:00", "sT": "12:00:00", "dayAbbrevs": "MoWeFr"}], "isPri": true, "status": {"description": "Open", "code": "O"}, "assocPriSecId": 13106, "id": 13106, "number": "001"}], "crossListed": null, "instructionMode": "P"}]}