{"380": [{"enrollment": {"wMax": 0, "eCurr": 0, "eMin": 0, "wCurr": 0, "eMax": 25}, "title": "Language Proficiency Workshop", "grading": "SUS", "instructionMode": "P", "id": 46048, "number": "001", "status": "A", "description": null, "crossListed": null, "units": {"maximum": 2, "minimum": 2}, "fExam": {"code": "N", "description": "No"}, "cN": "380", "priComp": "SEM", "sections": [{"id": 46048, "number": "001", "graded": true, "assocPriSecId": 46048, "status": {"code": "O", "description": "Open"}, "type": "SEM", "enrollment": {"wMax": 0, "eCurr": 0, "eMin": 0, "wCurr": 0, "eMax": 25}, "isPri": true, "meetings": [{"dayAbbrevs": "Tu", "instructors": [], "sT": "15:00:00", "days": {"Th": false, "We": false, "Tu": true, "Mo": false, "Su": false, "Fr": false, "Sa": false}, "loc": {}, "eT": "17:59:00"}]}], "sAC": "LANPRO"}]}